{
  "dynamo": {
    "local": {
      "url": "http://localhost:8000"
    },
    "tableName": "MyLocalTable",
    "createTable": true
  },
  "instance": {
    "port": 4000,
    "cors":{
      "Access-Control-Allow-Origin": "*",
      "Access-Control-Allow-Methods": "GET,PUT,POST,DELETE,OPTION",
      "Access-Control-Allow-Headers": "Content-Type, Authorization, Content-Length, X-msm-Sig, X-msm-Pass"
    }
  },
  "welcome": {
    "title": "Welcome to ySyPyA",
    "content": "Welcome,\n\nySyPyA stands for \"your Security your Privacy your Anonymity\"\nYour account is now activated.\n\nIf it's the first time you create an account, we urge you to visit the About page in the menu in the top right corner.\n\nThe ySyPyA team."
  },
  "timer": {
    "removal": {
      "session": 900000,
      "user": 600000,
      "frozen": 7776000000
    },
    "interval": {
      "poll": 120000
    }
  }
}
